[
    {
        "slug": "real-estate",
        "name": "Real Estate",
        "use_case": "Property Tracking & Client Matching",
        "hero_title": "The AI Realtor Assistant",
        "description": "Automate property inquiries, schedule viewings, and match clients to listings instantly with BasaltCRM's predictive engine.",
        "meta_title": "Best AI CRM for Real Estate | BasaltCRM",
        "meta_description": "Real Estate CRM for agents and brokerages with automated lead capture, property-matching AI, tour scheduling, workflows, and compliance tooling.",
        "keywords": [
            "Real Estate CRM",
            "Realtor CRM",
            "Broker CRM",
            "Property Matching AI",
            "Showing Scheduler",
            "Lead Capture"
        ],
        "subheading": "Grow listings, shorten cycles, delight buyers and sellers",
        "static_sections": {
            "features": {
                "core": [
                    "Unified contacts, properties, listings, and offers",
                    "Omnichannel capture (web forms, portals, email, phone, chat)",
                    "Predictive lead scoring and intent detection",
                    "Automated follow-up sequences and reminders",
                    "Custom pipelines and multi-stage approval flows",
                    "Tasks, notes, mentions, and activity timelines",
                    "Advanced search, filters, and saved views",
                    "Role-based access control and team workspaces",
                    "Bulk actions and automation triggers",
                    "Open API and Webhooks for extensibility"
                ],
                "analytics": [
                    "KPI dashboards for pipeline, conversion, and cycle times",
                    "Forecasting by segment, agent, team, and region",
                    "Attribution and campaign ROI tracking",
                    "Cohort analysis and churn risk insights"
                ],
                "ai_agents": [
                    "Inbound triage agent for new inquiries",
                    "Outbound nurture agent for cold/warm leads",
                    "Retention agent for at-risk accounts",
                    "Scheduling agent for tours and meetings",
                    "Support agent for FAQs and knowledge base"
                ]
            },
            "automation_playbooks": [
                "Lead intake → auto-qualification → agent assignment",
                "Property match suggestions → tour scheduling → feedback capture",
                "Offer pipeline movement → signature → close checklist",
                "Post-close nurture → referral program → repeat listings"
            ],
            "integrations": {
                "email_calendar": [
                    "Gmail",
                    "Outlook 365",
                    "Google Calendar",
                    "iCal"
                ],
                "communications": [
                    "Twilio/Voice",
                    "WhatsApp",
                    "SMS",
                    "Slack"
                ],
                "documents": [
                    "Google Drive",
                    "Dropbox",
                    "DocuSign",
                    "Adobe Sign"
                ],
                "marketing": [
                    "HubSpot forms",
                    "Meta Lead Ads",
                    "Google Ads"
                ],
                "data": [
                    "Snowflake",
                    "BigQuery",
                    "S3",
                    "CSV import/export"
                ]
            },
            "data_model": {
                "entities": [
                    "Contact",
                    "Account",
                    "Property/Listing",
                    "Deal/Offer",
                    "Interaction/Task",
                    "Campaign",
                    "Document"
                ],
                "relationships": [
                    "Account ↔ Contacts (1:N)",
                    "Contact ↔ Listings (N:M)",
                    "Deal ↔ Listings (1:N)",
                    "Deal ↔ Documents (N:M)"
                ]
            },
            "compliance": {
                "regions": [
                    "GDPR (EU/UK)",
                    "CCPA/CPRA (US)",
                    "PIPEDA (CA)",
                    "LGPD (BR)",
                    "PDPA (SG/MY)",
                    "POPIA (ZA)"
                ],
                "capabilities": [
                    "Consent tracking and audit trails",
                    "Data subject rights tooling (export, delete, rectify)",
                    "Encryption at rest and in transit",
                    "Configurable retention policies",
                    "Access controls and approvals"
                ]
            },
            "security": {
                "certifications": [
                    "SOC 2 Type II (patterns)",
                    "ISO 27001 aligned practices"
                ],
                "controls": [
                    "RBAC and SSO/SAML/OIDC",
                    "Field-level permissions",
                    "API keys with scoped tokens",
                    "IP allowlists and session policies"
                ]
            },
            "pricing_overview": {
                "model": "Transparent per-seat pricing, tailored for your team scale",
                "includes": [
                    "Core CRM modules",
                    "AI agents (sales, support, scheduling)",
                    "Dashboards and analytics",
                    "Open API access"
                ],
                "optional": [
                    "Premium support SLA",
                    "Dedicated region hosting",
                    "Professional services"
                ]
            },
            "onboarding": [
                "Discovery and requirements mapping",
                "Data import (CSV/API) and field mapping",
                "Workflow and pipeline configuration",
                "Integration setup (email/calendar/voice)",
                "AI agent tuning and go-live"
            ],
            "migration_guide": [
                "Export data from legacy CRM",
                "Normalize and validate schemas",
                "Import into BasaltCRM with mappings",
                "Recreate pipelines and automations",
                "User training and parallel run",
                "Cutover and decommission legacy"
            ],
            "support_sla": {
                "standard": "Business hours, 24–48h response, knowledge base access",
                "premium": "24/7 support, 1–4h response, dedicated CSM, quarterly reviews"
            },
            "faqs": [
                {
                    "q": "Can I self-host?",
                    "a": "Yes. Kubernetes/Helm supported. Cloud hosting also available."
                },
                {
                    "q": "Is there an API?",
                    "a": "Yes. REST and Webhooks with scoped tokens and rate limits."
                },
                {
                    "q": "Do you offer templates?",
                    "a": "Yes. Email, messaging, pipelines, and dashboards templates included."
                },
                {
                    "q": "How does AI train?",
                    "a": "AI uses organization-specific signals; no cross-tenant data mixing."
                }
            ]
        }
    },
    {
        "slug": "healthcare",
        "name": "Healthcare",
        "use_case": "Patient Engagement & HIPAA Compliance",
        "hero_title": "Secure Patient Relationship Management",
        "description": "Manage patient intake, appointment reminders, and follow-ups with bank-grade security and HIPAA-compliant infrastructure.",
        "meta_title": "Best AI CRM for Healthcare | BasaltCRM",
        "meta_description": "Healthcare CRM with HIPAA-aware workflows, patient intake automation, appointment reminders, secure messaging, and audit trails.",
        "keywords": [
            "Healthcare CRM",
            "HIPAA CRM",
            "Patient Engagement",
            "Medical Practice CRM",
            "Secure Messaging"
        ],
        "subheading": "Personalized care at scale",
        "static_sections": {
            "$ref": "STATIC_BASE"
        }
    },
    {
        "slug": "legal",
        "name": "Legal",
        "use_case": "Case Management & Client Intake",
        "hero_title": "Automate Your Law Practice",
        "description": "From client intake to case updates, let AI handle the administrative burden so you can focus on winning cases.",
        "meta_title": "Best AI CRM for Law Firms | BasaltCRM",
        "meta_description": "Legal CRM for intake, case tracking, document automation, deadlines, and client communication in one secure platform.",
        "keywords": [
            "Legal CRM",
            "Law Firm CRM",
            "Case Management",
            "Client Intake",
            "Document Automation"
        ],
        "subheading": "Streamline matters, improve outcomes",
        "static_sections": {
            "$ref": "STATIC_BASE"
        }
    },
    {
        "slug": "finance",
        "name": "Financial Services",
        "use_case": "Wealth Management & Client Onboarding",
        "hero_title": "Smart Wealth Management CRM",
        "description": "Predict client needs, automate onboarding, and ensure compliance with a CRM built for the modern financial advisor.",
        "meta_title": "Best AI CRM for Financial Services | BasaltCRM",
        "meta_description": "Financial CRM for wealth advisory and banking with onboarding automation, compliance logging, and predictive analytics.",
        "keywords": [
            "Finance CRM",
            "Wealth Management CRM",
            "Advisor CRM",
            "Compliance CRM"
        ],
        "subheading": "Trust, transparency, and growth",
        "static_sections": {
            "$ref": "STATIC_BASE"
        }
    },
    {
        "slug": "ecommerce",
        "name": "E-commerce",
        "use_case": "Customer Support & Order Recovery",
        "hero_title": "Turn Support into Sales",
        "description": "Recover abandoned carts and solve support tickets instantly. BasaltCRM integrates with your store to drive revenue 24/7.",
        "meta_title": "Best AI CRM for E-commerce | BasaltCRM",
        "meta_description": "E-commerce CRM with order recovery, support automation, personalized campaigns, and predictive product recommendations.",
        "keywords": [
            "E-commerce CRM",
            "Cart Recovery",
            "Support Automation",
            "Customer Loyalty"
        ],
        "subheading": "Reduce churn, increase LTV",
        "static_sections": {
            "$ref": "STATIC_BASE"
        }
    },
    {
        "slug": "saas",
        "name": "SaaS",
        "use_case": "Customer Success & Churn Prevention",
        "hero_title": "Reduce Churn with AI",
        "description": "Identify at-risk customers before they leave. BasaltCRM predicts churn and automates proactive outreach to keep them engaged.",
        "meta_title": "Best AI CRM for SaaS | BasaltCRM",
        "meta_description": "SaaS CRM with health scoring, expansion playbooks, renewal pipelines, and proactive success automation.",
        "keywords": [
            "SaaS CRM",
            "Customer Success",
            "Churn Prevention",
            "Renewals"
        ],
        "subheading": "Drive adoption and expansions",
        "static_sections": {
            "$ref": "STATIC_BASE"
        }
    },
    {
        "slug": "manufacturing",
        "name": "Manufacturing",
        "use_case": "Supply Chain & B2B Sales",
        "hero_title": "Streamline B2B Operations",
        "description": "Manage complex B2B relationships, track orders, and predict inventory needs with industry-specific AI.",
        "meta_title": "Best AI CRM for Manufacturing | BasaltCRM",
        "meta_description": "Manufacturing CRM for B2B accounts, orders, supplier management, and predictive inventory workflows.",
        "keywords": [
            "Manufacturing CRM",
            "B2B Sales CRM",
            "Supplier Management",
            "Order Tracking"
        ],
        "subheading": "Operational visibility across the chain",
        "static_sections": {
            "$ref": "STATIC_BASE"
        }
    },
    {
        "slug": "consulting",
        "name": "Consulting",
        "use_case": "Project Tracking & Client Billing",
        "hero_title": "All-in-One Consulting CRM",
        "description": "Track projects, automate invoicing, and nurture client relationships without switching between tools.",
        "meta_title": "Best AI CRM for Consulting | BasaltCRM",
        "meta_description": "Consulting CRM with project pipelines, billing automation, client portals, and AI-based engagement.",
        "keywords": [
            "Consulting CRM",
            "Professional Services CRM",
            "Project CRM",
            "Billing Automation"
        ],
        "subheading": "Deliver value on time, every time",
        "static_sections": {
            "$ref": "STATIC_BASE"
        }
    },
    {
        "slug": "insurance",
        "name": "Insurance",
        "use_case": "Policy Management & Claims Processing",
        "hero_title": "Accelerate Policy Sales",
        "description": "Automate policy recommendations and claims follow-ups, giving your agents more time to build trust with clients.",
        "meta_title": "Best AI CRM for Insurance | BasaltCRM",
        "meta_description": "Insurance CRM for policies, claims, renewals, and agent productivity with predictive recommendations.",
        "keywords": [
            "Insurance CRM",
            "Policy CRM",
            "Claims CRM",
            "Agent CRM"
        ],
        "subheading": "Trusted relationships at scale",
        "static_sections": {
            "$ref": "STATIC_BASE"
        }
    },
    {
        "slug": "education",
        "name": "Education",
        "use_case": "Student Enrollment & Alumni Engagement",
        "hero_title": "Manage the Student Journey",
        "description": "From prospective students to proud alumni, nurture every relationship with personalized AI-driven communication.",
        "meta_title": "Best AI CRM for Education | BasaltCRM",
        "meta_description": "Education CRM for recruitment, enrollment, engagement, and alumni relations with predictive outreach.",
        "keywords": [
            "Education CRM",
            "Student CRM",
            "Admissions CRM",
            "Alumni Engagement"
        ],
        "subheading": "Personalized journeys from inquiry to alumni",
        "static_sections": {
            "$ref": "STATIC_BASE"
        }
    },
    {
        "slug": "hospitality",
        "name": "Hospitality",
        "use_case": "Guest Management & Reservations",
        "hero_title": "Deliver 5-Star Guest Experiences",
        "description": "Predict guest preferences, automate upsells, and ensure every stay is memorable with AI-powered hospitality.",
        "meta_title": "Best AI CRM for Hospitality | BasaltCRM",
        "meta_description": "Hospitality CRM for reservations, upsells, loyalty, and guest engagement with predictive personalization.",
        "keywords": [
            "Hospitality CRM",
            "Guest CRM",
            "Reservation CRM",
            "Upsell Automation"
        ],
        "subheading": "Memorable stays, measurable ROI",
        "static_sections": {
            "$ref": "STATIC_BASE"
        }
    },
    {
        "slug": "automotive",
        "name": "Automotive",
        "use_case": "Lead Tracking & Service Scheduling",
        "hero_title": "Drive More Test Drives",
        "description": "Convert online browsers into showroom visitors with predictive lead scoring and automated follow-up.",
        "meta_title": "Best AI CRM for Automotive | BasaltCRM",
        "meta_description": "Automotive CRM for dealership sales, service scheduling, and customer retention with predictive scoring.",
        "keywords": [
            "Automotive CRM",
            "Dealership CRM",
            "Service Scheduling",
            "Lead Scoring"
        ],
        "subheading": "From clicks to keys with AI",
        "static_sections": {
            "$ref": "STATIC_BASE"
        }
    },
    {
        "slug": "nonprofit",
        "name": "Non-Profit",
        "use_case": "Donor Management & Campaign Tracking",
        "hero_title": "Maximize Donor Impact",
        "description": "Identify major donors, automate thank-you campaigns, and increase giving with AI-driven stewardship.",
        "meta_title": "Best AI CRM for Non-Profits | BasaltCRM",
        "meta_description": "Non-profit CRM with donor management, campaigns, stewardship automation, and impact reporting.",
        "keywords": [
            "Non-profit CRM",
            "Donor CRM",
            "Fundraising CRM",
            "Campaign CRM"
        ],
        "subheading": "Build lasting donor relationships",
        "static_sections": {
            "$ref": "STATIC_BASE"
        }
    },
    {
        "slug": "construction",
        "name": "Construction",
        "use_case": "Project Bidding & Client Relations",
        "hero_title": "Win More Bids",
        "description": "Track project pipelines, manage subcontractor relationships, and never miss a bid deadline.",
        "meta_title": "Best AI CRM for Construction | BasaltCRM",
        "meta_description": "Construction CRM for bid management, subcontractors, project pipelines, and service workflows.",
        "keywords": [
            "Construction CRM",
            "Bid CRM",
            "Project CRM",
            "Subcontractor Management"
        ],
        "subheading": "Predictable projects, profitable bids",
        "static_sections": {
            "$ref": "STATIC_BASE"
        }
    },
    {
        "slug": "retail",
        "name": "Retail",
        "use_case": "Customer Loyalty & Inventory",
        "hero_title": "Omnichannel Retail Excellence",
        "description": "Unify in-store and online customer data to deliver personalized experiences that drive loyalty.",
        "meta_title": "Best AI CRM for Retail | BasaltCRM",
        "meta_description": "Retail CRM for loyalty programs, personalized outreach, omnichannel service, and inventory-aware campaigns.",
        "keywords": [
            "Retail CRM",
            "Loyalty CRM",
            "Omnichannel CRM",
            "Personalization"
        ],
        "subheading": "Personalized experiences, repeat purchases",
        "static_sections": {
            "$ref": "STATIC_BASE"
        }
    },
    {
        "slug": "agriculture",
        "name": "Agriculture",
        "use_case": "Buyer Relations & Supply Management",
        "hero_title": "Grow Your Agribusiness",
        "description": "Manage crop buyers, distributors, and suppliers with a CRM built for the agriculture industry.",
        "meta_title": "Best AI CRM for Agriculture | BasaltCRM",
        "meta_description": "Agriculture CRM for buyer relations, distributors, supplier management, and seasonal operations.",
        "keywords": [
            "Agriculture CRM",
            "Agri CRM",
            "Buyer Relations",
            "Supplier CRM"
        ],
        "subheading": "From farm to market with visibility",
        "static_sections": {
            "$ref": "STATIC_BASE"
        }
    },
    {
        "slug": "energy",
        "name": "Energy & Utilities",
        "use_case": "Account Management & Service Requests",
        "hero_title": "Power Customer Relationships",
        "description": "Handle service requests, manage accounts, and reduce churn with predictive analytics for utilities.",
        "meta_title": "Best AI CRM for Energy & Utilities | BasaltCRM",
        "meta_description": "Energy CRM for service requests, account operations, and predictive analytics to reduce churn.",
        "keywords": [
            "Energy CRM",
            "Utilities CRM",
            "Service Requests",
            "Predictive Analytics"
        ],
        "subheading": "Reliable service with proactive outreach",
        "static_sections": {
            "$ref": "STATIC_BASE"
        }
    },
    {
        "slug": "telecom",
        "name": "Telecommunications",
        "use_case": "Subscription Management & Support",
        "hero_title": "Reduce Telecom Churn",
        "description": "Predict which subscribers are at risk and automate retention campaigns to keep them connected.",
        "meta_title": "Best AI CRM for Telecom | BasaltCRM",
        "meta_description": "Telecom CRM for subscriptions, support automation, retention campaigns, and usage insights.",
        "keywords": [
            "Telecom CRM",
            "Subscription CRM",
            "Support CRM",
            "Retention"
        ],
        "subheading": "Stay connected, stay retained",
        "static_sections": {
            "$ref": "STATIC_BASE"
        }
    },
    {
        "slug": "media",
        "name": "Media & Entertainment",
        "use_case": "Advertising Sales & Audience Engagement",
        "hero_title": "Monetize Your Audience",
        "description": "Track advertiser relationships, manage campaigns, and maximize ad revenue with intelligent CRM.",
        "meta_title": "Best AI CRM for Media | BasaltCRM",
        "meta_description": "Media CRM for advertising sales, audience engagement, campaign tracking, and revenue analytics.",
        "keywords": [
            "Media CRM",
            "Advertising CRM",
            "Audience CRM",
            "Campaign CRM"
        ],
        "subheading": "Engaged audiences, optimized revenue",
        "static_sections": {
            "$ref": "STATIC_BASE"
        }
    },
    {
        "slug": "logistics",
        "name": "Logistics",
        "use_case": "Client Shipping & Route Optimization",
        "hero_title": "Ship Smarter",
        "description": "Manage client accounts, optimize routes, and ensure on-time delivery with logistics-focused CRM.",
        "meta_title": "Best AI CRM for Logistics | BasaltCRM",
        "meta_description": "Logistics CRM for shipment, routing, ETAs, client accounts, and predictive delivery performance.",
        "keywords": [
            "Logistics CRM",
            "Shipping CRM",
            "Route Optimization",
            "Delivery ETA"
        ],
        "subheading": "Predictive routing, reliable ETAs",
        "static_sections": {
            "$ref": "STATIC_BASE"
        }
    },
    {
        "slug": "fitness",
        "name": "Fitness & Wellness",
        "use_case": "Member Management & Class Scheduling",
        "hero_title": "Grow Your Gym",
        "description": "Automate class bookings, track member engagement, and reduce cancellations with predictive outreach.",
        "meta_title": "Best AI CRM for Fitness & Wellness | BasaltCRM",
        "meta_description": "Fitness CRM for memberships, class schedules, outreach, and retention automation.",
        "keywords": [
            "Fitness CRM",
            "Gym CRM",
            "Class Scheduling",
            "Member Retention"
        ],
        "subheading": "Engaged members, full classes",
        "static_sections": {
            "$ref": "STATIC_BASE"
        }
    },
    {
        "slug": "travel",
        "name": "Travel & Tourism",
        "use_case": "Booking Management & Customer Loyalty",
        "hero_title": "Create Unforgettable Journeys",
        "description": "Manage bookings, personalize travel recommendations, and build lifelong customer relationships.",
        "meta_title": "Best AI CRM for Travel | BasaltCRM",
        "meta_description": "Travel CRM with bookings, personalization, loyalty programs, and upsell automation.",
        "keywords": [
            "Travel CRM",
            "Tourism CRM",
            "Booking CRM",
            "Personalization"
        ],
        "subheading": "Personalized trips, repeat travelers",
        "static_sections": {
            "$ref": "STATIC_BASE"
        }
    },
    {
        "slug": "pharmaceutical",
        "name": "Pharmaceutical",
        "use_case": "Physician Relations & Sample Tracking",
        "hero_title": "Accelerate Drug Sales",
        "description": "Track physician relationships, manage sample distribution, and comply with industry regulations.",
        "meta_title": "Best AI CRM for Pharmaceutical | BasaltCRM",
        "meta_description": "Pharma CRM for physician relations, samples, compliance logs, and predictive outreach.",
        "keywords": [
            "Pharmaceutical CRM",
            "Physician CRM",
            "Sample Management",
            "Compliance CRM"
        ],
        "subheading": "Precision outreach, compliant operations",
        "static_sections": {
            "$ref": "STATIC_BASE"
        }
    },
    {
        "slug": "recruitment",
        "name": "Recruitment",
        "use_case": "Candidate Tracking & Client Placement",
        "hero_title": "Fill Roles Faster",
        "description": "Match candidates to jobs with AI, automate outreach, and streamline the entire hiring process.",
        "meta_title": "Best AI CRM for Recruitment | BasaltCRM",
        "meta_description": "Recruitment CRM for candidate pipelines, client placement, automation, and interview scheduling.",
        "keywords": [
            "Recruitment CRM",
            "ATS CRM",
            "Staffing CRM",
            "Candidate Matching"
        ],
        "subheading": "Better matches, faster placements",
        "static_sections": {
            "$ref": "STATIC_BASE"
        }
    },
    {
        "slug": "property-management",
        "name": "Property Management",
        "use_case": "Tenant Relations & Lease Management",
        "hero_title": "Simplify Property Management",
        "description": "Track tenants, automate rent reminders, and handle maintenance requests all in one place.",
        "meta_title": "Best AI CRM for Property Management | BasaltCRM",
        "meta_description": "Property management CRM for tenants, leases, reminders, maintenance, and inspections.",
        "keywords": [
            "Property Management CRM",
            "Tenant CRM",
            "Lease CRM",
            "Maintenance CRM"
        ],
        "subheading": "Fewer vacancies, smoother operations",
        "static_sections": {
            "$ref": "STATIC_BASE"
        }
    },
    {
        "slug": "architecture",
        "name": "Architecture",
        "use_case": "Client Projects & Design Collaboration",
        "hero_title": "Build Better Client Relationships",
        "description": "Manage design projects, track client feedback, and streamline approvals with visual CRM.",
        "meta_title": "Best AI CRM for Architecture | BasaltCRM",
        "meta_description": "Architecture CRM for projects, client feedback cycles, approvals, and document collaboration.",
        "keywords": [
            "Architecture CRM",
            "Design CRM",
            "Project CRM",
            "Client Collaboration"
        ],
        "subheading": "Clarity in collaboration",
        "static_sections": {
            "$ref": "STATIC_BASE"
        }
    },
    {
        "slug": "accounting",
        "name": "Accounting",
        "use_case": "Client Billing & Tax Season Management",
        "hero_title": "Grow Your Practice",
        "description": "Track client engagements, automate invoice reminders, and never miss a filing deadline.",
        "meta_title": "Best AI CRM for Accounting | BasaltCRM",
        "meta_description": "Accounting CRM for engagements, invoicing, reminders, document requests, and seasonal workflows.",
        "keywords": [
            "Accounting CRM",
            "Tax CRM",
            "Billing CRM",
            "Client Engagement"
        ],
        "subheading": "Predictable billing, happy clients",
        "static_sections": {
            "$ref": "STATIC_BASE"
        }
    },
    {
        "slug": "event-planning",
        "name": "Event Planning",
        "use_case": "Vendor Management & Client Coordination",
        "hero_title": "Plan Flawless Events",
        "description": "Coordinate vendors, manage client expectations, and ensure every event is a success.",
        "meta_title": "Best AI CRM for Event Planning | BasaltCRM",
        "meta_description": "Event planning CRM for vendors, timelines, budgets, RSVPs, and post-event follow-ups.",
        "keywords": [
            "Event Planning CRM",
            "Vendor CRM",
            "RSVP CRM",
            "Timeline Management"
        ],
        "subheading": "Every detail, every deadline",
        "static_sections": {
            "$ref": "STATIC_BASE"
        }
    },
    {
        "slug": "security",
        "name": "Security Services",
        "use_case": "Contract Management & Incident Tracking",
        "hero_title": "Protect and Serve",
        "description": "Manage security contracts, track incidents, and ensure client safety with intelligent CRM.",
        "meta_title": "Best AI CRM for Security Services | BasaltCRM",
        "meta_description": "Security CRM for contracts, patrol schedules, incident tracking, and client reporting.",
        "keywords": [
            "Security CRM",
            "Incident CRM",
            "Contract CRM",
            "Patrol Scheduling"
        ],
        "subheading": "Visibility and accountability",
        "static_sections": {
            "$ref": "STATIC_BASE"
        }
    },
    {
        "slug": "cleaning",
        "name": "Cleaning Services",
        "use_case": "Scheduling & Customer Retention",
        "hero_title": "Keep Clients Coming Back",
        "description": "Automate scheduling, send service reminders, and build a loyal customer base.",
        "meta_title": "Best AI CRM for Cleaning Services | BasaltCRM",
        "meta_description": "Cleaning CRM for scheduling, reminders, crew assignments, invoicing, and repeat bookings.",
        "keywords": [
            "Cleaning CRM",
            "Scheduling CRM",
            "Service Reminders",
            "Crew Management"
        ],
        "subheading": "Reliable service, repeat business",
        "static_sections": {
            "$ref": "STATIC_BASE"
        }
    },
    {
        "slug": "photography",
        "name": "Photography",
        "use_case": "Booking Management & Portfolio Sharing",
        "hero_title": "Capture More Clients",
        "description": "Manage bookings, share portfolios, and automate follow-ups to grow your photography business.",
        "meta_title": "Best AI CRM for Photographers | BasaltCRM",
        "meta_description": "Photography CRM for bookings, portfolio sharing, contracts, proofs, and follow-ups.",
        "keywords": [
            "Photography CRM",
            "Booking CRM",
            "Portfolio CRM",
            "Proofing"
        ],
        "subheading": "From inquiry to album delivery",
        "static_sections": {
            "$ref": "STATIC_BASE"
        }
    },
    {
        "slug": "veterinary",
        "name": "Veterinary",
        "use_case": "Pet Records & Appointment Reminders",
        "hero_title": "Care for Pets and Owners",
        "description": "Track pet health records, send vaccination reminders, and build lasting relationships with pet owners.",
        "meta_title": "Best AI CRM for Veterinary Clinics | BasaltCRM",
        "meta_description": "Veterinary CRM for records, reminders, bookings, and owner communication.",
        "keywords": [
            "Veterinary CRM",
            "Pet CRM",
            "Appointment CRM",
            "Vaccination Reminders"
        ],
        "subheading": "Health records and happy owners",
        "static_sections": {
            "$ref": "STATIC_BASE"
        }
    },
    {
        "slug": "beauty",
        "name": "Beauty & Salon",
        "use_case": "Appointment Booking & Product Sales",
        "hero_title": "Beautify Your Business",
        "description": "Manage appointments, track product preferences, and increase retail sales with salon CRM.",
        "meta_title": "Best AI CRM for Beauty & Salon | BasaltCRM",
        "meta_description": "Salon CRM for bookings, product sales, memberships, promotions, and retention.",
        "keywords": [
            "Salon CRM",
            "Beauty CRM",
            "Booking CRM",
            "Retail Sales"
        ],
        "subheading": "Booked calendars, loyal clients",
        "static_sections": {
            "$ref": "STATIC_BASE"
        }
    },
    {
        "slug": "food-service",
        "name": "Food Service",
        "use_case": "Catering & Customer Loyalty",
        "hero_title": "Serve Up Success",
        "description": "Manage catering orders, track customer preferences, and build a database of loyal diners.",
        "meta_title": "Best AI CRM for Food Service | BasaltCRM",
        "meta_description": "Food service CRM for catering, reservations, preferences, promotions, and loyalty.",
        "keywords": [
            "Food Service CRM",
            "Catering CRM",
            "Restaurant CRM",
            "Loyalty"
        ],
        "subheading": "Full tables and repeat orders",
        "static_sections": {
            "$ref": "STATIC_BASE"
        }
    },
    {
        "slug": "plumbing",
        "name": "Plumbing",
        "use_case": "Service Calls & Emergency Dispatch",
        "hero_title": "Fix Leaks, Build Relationships",
        "description": "Dispatch technicians, track service history, and automate follow-ups for repeat business.",
        "meta_title": "Best AI CRM for Plumbing | BasaltCRM",
        "meta_description": "Plumbing CRM for dispatch, scheduling, history, invoicing, and maintenance contracts.",
        "keywords": [
            "Plumbing CRM",
            "Dispatch CRM",
            "Service CRM",
            "Maintenance Contracts"
        ],
        "subheading": "Fast response, loyal customers",
        "static_sections": {
            "$ref": "STATIC_BASE"
        }
    },
    {
        "slug": "electrical",
        "name": "Electrical Services",
        "use_case": "Project Bidding & Safety Compliance",
        "hero_title": "Power Your Business Growth",
        "description": "Manage electrical projects, track compliance, and win more bids with intelligent CRM.",
        "meta_title": "Best AI CRM for Electrical Services | BasaltCRM",
        "meta_description": "Electrical CRM for bids, projects, compliance, scheduling, and documentation.",
        "keywords": [
            "Electrical CRM",
            "Project CRM",
            "Compliance CRM",
            "Bidding"
        ],
        "subheading": "Safe projects, stronger margins",
        "static_sections": {
            "$ref": "STATIC_BASE"
        }
    },
    {
        "slug": "hvac",
        "name": "HVAC",
        "use_case": "Maintenance Contracts & Seasonal Campaigns",
        "hero_title": "Stay Top of Mind",
        "description": "Automate seasonal maintenance reminders and convert one-time repairs into annual contracts.",
        "meta_title": "Best AI CRM for HVAC | BasaltCRM",
        "meta_description": "HVAC CRM for seasonal campaigns, dispatch, service history, and contract renewals.",
        "keywords": [
            "HVAC CRM",
            "Maintenance CRM",
            "Seasonal Campaigns",
            "Dispatch"
        ],
        "subheading": "Proactive care and renewals",
        "static_sections": {
            "$ref": "STATIC_BASE"
        }
    },
    {
        "slug": "landscaping",
        "name": "Landscaping",
        "use_case": "Property Management & Seasonal Services",
        "hero_title": "Grow Your Green Business",
        "description": "Manage property accounts, track seasonal services, and automate renewal campaigns.",
        "meta_title": "Best AI CRM for Landscaping | BasaltCRM",
        "meta_description": "Landscaping CRM for properties, schedules, crews, invoicing, and renewals.",
        "keywords": [
            "Landscaping CRM",
            "Property CRM",
            "Crew Scheduling",
            "Renewals"
        ],
        "subheading": "Beautiful properties, predictable revenue",
        "static_sections": {
            "$ref": "STATIC_BASE"
        }
    },
    {
        "slug": "pest-control",
        "name": "Pest Control",
        "use_case": "Treatment Scheduling & Follow-Up",
        "hero_title": "Eliminate Pests, Not Customers",
        "description": "Schedule treatments, send follow-up reminders, and ensure customer satisfaction with every visit.",
        "meta_title": "Best AI CRM for Pest Control | BasaltCRM",
        "meta_description": "Pest control CRM for treatments, schedules, reminders, and follow-up automation.",
        "keywords": [
            "Pest Control CRM",
            "Treatment CRM",
            "Scheduling",
            "Follow-Up"
        ],
        "subheading": "On-time treatments, long-term relationships",
        "static_sections": {
            "$ref": "STATIC_BASE"
        }
    },
    {
        "slug": "moving",
        "name": "Moving Services",
        "use_case": "Quote Management & Logistics",
        "hero_title": "Move Relationships Forward",
        "description": "Manage quotes, coordinate logistics, and turn one-time movers into referral sources.",
        "meta_title": "Best AI CRM for Moving Services | BasaltCRM",
        "meta_description": "Moving CRM for quotes, bookings, logistics, crew assignments, and follow-up.",
        "keywords": [
            "Moving CRM",
            "Quote CRM",
            "Logistics",
            "Crew Management"
        ],
        "subheading": "Smooth moves, strong referrals",
        "static_sections": {
            "$ref": "STATIC_BASE"
        }
    },
    {
        "slug": "wedding",
        "name": "Wedding Services",
        "use_case": "Vendor Coordination & Timeline Management",
        "hero_title": "Create Perfect Weddings",
        "description": "Coordinate all wedding vendors, manage timelines, and ensure every couple's dream comes true.",
        "meta_title": "Best AI CRM for Wedding Services | BasaltCRM",
        "meta_description": "Wedding CRM for vendors, timelines, budgets, RSVPs, and post-event galleries.",
        "keywords": [
            "Wedding CRM",
            "Vendor CRM",
            "Timeline CRM",
            "RSVP"
        ],
        "subheading": "Perfect coordination for perfect days",
        "static_sections": {
            "$ref": "STATIC_BASE"
        }
    },
    {
        "slug": "printing",
        "name": "Printing Services",
        "use_case": "Order Tracking & Design Approval",
        "hero_title": "Print More, Stress Less",
        "description": "Manage print orders, track design approvals, and automate reorder reminders for repeat clients.",
        "meta_title": "Best AI CRM for Printing Services | BasaltCRM",
        "meta_description": "Printing CRM for orders, design approvals, proofs, production, and reorders.",
        "keywords": [
            "Printing CRM",
            "Order CRM",
            "Proofing",
            "Reorder Automation"
        ],
        "subheading": "On-time print, on-point quality",
        "static_sections": {
            "$ref": "STATIC_BASE"
        }
    },
    {
        "slug": "warehousing",
        "name": "Warehousing",
        "use_case": "Client Inventory & Billing",
        "hero_title": "Store Smarter",
        "description": "Track client inventory, automate billing cycles, and optimize warehouse operations.",
        "meta_title": "Best AI CRM for Warehousing | BasaltCRM",
        "meta_description": "Warehousing CRM for client inventory, billing cycles, SLAs, and operations analytics.",
        "keywords": [
            "Warehousing CRM",
            "Inventory CRM",
            "Billing",
            "Operations"
        ],
        "subheading": "Visibility, velocity, value",
        "static_sections": {
            "$ref": "STATIC_BASE"
        }
    },
    {
        "slug": "translation",
        "name": "Translation Services",
        "use_case": "Project Management & Linguist Coordination",
        "hero_title": "Translate to Success",
        "description": "Manage translation projects, coordinate linguists, and deliver on time, every time.",
        "meta_title": "Best AI CRM for Translation Services | BasaltCRM",
        "meta_description": "Translation CRM for projects, linguist assignment, QA, deliveries, and billing.",
        "keywords": [
            "Translation CRM",
            "Localization CRM",
            "Project Management",
            "Linguist Coordination"
        ],
        "subheading": "Quality translations, predictable delivery",
        "static_sections": {
            "$ref": "STATIC_BASE"
        }
    },
    {
        "slug": "marketing-agency",
        "name": "Marketing Agency",
        "use_case": "Campaign Management & Client Reporting",
        "hero_title": "Scale Your Agency",
        "description": "Track client campaigns, automate reporting, and demonstrate ROI with data-driven insights.",
        "meta_title": "Best AI CRM for Marketing Agencies | BasaltCRM",
        "meta_description": "Agency CRM for campaigns, assets, approvals, client reporting, and upsell motions.",
        "keywords": [
            "Agency CRM",
            "Marketing CRM",
            "Campaign CRM",
            "Client Reporting"
        ],
        "subheading": "Repeatable process, repeatable profit",
        "static_sections": {
            "$ref": "STATIC_BASE"
        }
    },
    {
        "slug": "it-services",
        "name": "IT Services",
        "use_case": "Ticket Management & SLA Tracking",
        "hero_title": "Resolve Issues, Build Trust",
        "description": "Manage support tickets, track SLAs, and ensure every client stays operational.",
        "meta_title": "Best AI CRM for IT Services | BasaltCRM",
        "meta_description": "IT services CRM for tickets, SLAs, asset records, change logs, and client communication.",
        "keywords": [
            "IT Services CRM",
            "MSP CRM",
            "Ticketing",
            "SLA Tracking"
        ],
        "subheading": "Reliable service at scale",
        "static_sections": {
            "$ref": "STATIC_BASE"
        }
    },
    {
        "slug": "web-development",
        "name": "Web Development",
        "use_case": "Project Milestones & Client Feedback",
        "hero_title": "Build Better Websites",
        "description": "Track development milestones, collect client feedback, and deliver projects on time.",
        "meta_title": "Best AI CRM for Web Development | BasaltCRM",
        "meta_description": "Web development CRM for sprints, milestones, feedback loops, approvals, and handover.",
        "keywords": [
            "Web Development CRM",
            "Dev Agency CRM",
            "Project CRM",
            "Client Feedback"
        ],
        "subheading": "Aligned expectations, on-time delivery",
        "static_sections": {
            "$ref": "STATIC_BASE"
        }
    },
    {
        "slug": "government",
        "name": "Government",
        "use_case": "Constituent Services & Case Management",
        "hero_title": "Serve the Public Better",
        "description": "Track constituent requests, manage case files, and improve public service delivery.",
        "meta_title": "Best AI CRM for Government | BasaltCRM",
        "meta_description": "Government CRM for case management, services, audit logs, and citizen engagement tooling.",
        "keywords": [
            "Government CRM",
            "Public Sector CRM",
            "Case Management",
            "Constituent Services"
        ],
        "subheading": "Transparency and responsiveness",
        "static_sections": {
            "$ref": "STATIC_BASE"
        }
    },
    {
        "slug": "aviation",
        "name": "Aviation",
        "use_case": "Flight Scheduling & Passenger Relations",
        "hero_title": "Clear for Takeoff",
        "description": "Manage flight schedules, track passenger preferences, and ensure smooth operations.",
        "meta_title": "Best AI CRM for Aviation | BasaltCRM",
        "meta_description": "Aviation CRM for scheduling, passenger profiles, operations messaging, and service SLAs.",
        "keywords": [
            "Aviation CRM",
            "Airline CRM",
            "Passenger CRM",
            "Scheduling"
        ],
        "subheading": "Operational clarity, passenger delight",
        "static_sections": {
            "$ref": "STATIC_BASE"
        }
    },
    {
        "slug": "mining",
        "name": "Mining",
        "use_case": "Supplier Relations & Safety Compliance",
        "hero_title": "Extract More Value",
        "description": "Manage supplier contracts, track safety compliance, and optimize mining operations.",
        "meta_title": "Best AI CRM for Mining | BasaltCRM",
        "meta_description": "Mining CRM for suppliers, compliance logs, projects, and operational analytics.",
        "keywords": [
            "Mining CRM",
            "Supplier CRM",
            "Compliance CRM",
            "Project CRM"
        ],
        "subheading": "Coordinated operations, compliant practices",
        "static_sections": {
            "$ref": "STATIC_BASE"
        }
    }
]